godot_wsl_proxy/__init__.py
godot_wsl_proxy/__main__.py
godot_wsl_proxy/cli.py
godot_wsl_proxy/server.py
godot_wsl_proxy-0.2.1.dist-info/LICENSE
godot_wsl_proxy-0.2.1.dist-info/METADATA
godot_wsl_proxy-0.2.1.dist-info/WHEEL
godot_wsl_proxy-0.2.1.dist-info/entry_points.txt
godot_wsl_proxy-0.2.1.dist-info/RECORD
