Metadata-Version: 2.1
Name: godot-wsl-proxy
Version: 0.2.1
Summary: LSP proxy to work from editor located in WSL and Godot located in Windows seemlessly
Home-page: https://github.com/venomlab/godot-wsl-proxy
License: MIT
Author: Dmytro Selishchev
Author-email: zibertscrem@gmail.com
Requires-Python: >=3.11,<4.0
Classifier: License :: OSI Approved :: MIT License
Classifier: Programming Language :: Python :: 3
Classifier: Programming Language :: Python :: 3.11
Classifier: Programming Language :: Python :: 3.12
Requires-Dist: click (>=8.1.8,<8.2.0)
Project-URL: Repository, https://github.com/venomlab/godot-wsl-proxy
